LICENSE
README.md
setup.cfg
setup.py
orionsdk/__init__.py
orionsdk/solarwinds.py
orionsdk/swisclient.py
orionsdk.egg-info/PKG-INFO
orionsdk.egg-info/SOURCES.txt
orionsdk.egg-info/dependency_links.txt
orionsdk.egg-info/requires.txt
orionsdk.egg-info/top_level.txt