Metadata-Version: 2.4
Name: orionsdk
Version: 0.5.0
Summary: Python API for the SolarWinds Orion SDK
Home-page: http://github.com/solarwinds/orionsdk-python
Author: SolarWinds
Author-email: orionsdk@solarwinds.com
License: https://github.com/solarwinds/orionsdk-python/blob/master/LICENSE
Keywords: solarwinds swis orion orionsdk
Platform: Posix; MacOS X; Windows
Classifier: Development Status :: 3 - Alpha
Classifier: Intended Audience :: Developers
Classifier: License :: OSI Approved :: Apache Software License
Classifier: Operating System :: OS Independent
Classifier: Topic :: Internet
Classifier: Programming Language :: Python
Classifier: Programming Language :: Python :: 3
License-File: LICENSE
Requires-Dist: six
Requires-Dist: requests
Dynamic: author
Dynamic: author-email
Dynamic: classifier
Dynamic: home-page
Dynamic: keywords
Dynamic: license
Dynamic: license-file
Dynamic: platform
Dynamic: requires-dist
Dynamic: summary
